app/__init__.py
app/cli.py
app/constants.py
app/job.py
app/pipeline.py
app/sample_job.py
app/analyzer/__init__.py
app/analyzer/base.py
app/analyzer/output.py
app/analyzer/quality.py
app/dedup/__init__.py
app/dedup/base.py
app/dedup/semantic.py
app/format/__init__.py
app/format/base.py
app/format/conv.py
app/format/conv_text.py
app/format/dpo.py
app/format/merger.py
app/format/output.py
app/format/sft.py
app/format/to_text.py
app/helpers/__init__.py
app/helpers/call_openai.py
app/helpers/embeddings.py
app/helpers/logger.py
app/helpers/models.py
app/helpers/regex_dict.py
app/helpers/text_utils.py
app/helpers/types.py
app/helpers/utils.py
app/helpers/formatter/__init__.py
app/helpers/formatter/config.py
app/helpers/formatter/dataset.py
app/helpers/formatter/messages.py
app/helpers/formatter/text.py
app/loader/__init__.py
app/loader/base.py
app/loader/huggingface.py
app/loader/local_file.py
app/models/__init__.py
app/models/base.py
app/models/conv.py
app/models/messages.py
app/models/quality.py
app/saver/__init__.py
app/saver/base.py
app/saver/local.py
app/translators/__init__.py
app/translators/translator.py
datasetpipeline-0.2.1.dist-info/METADATA
datasetpipeline-0.2.1.dist-info/WHEEL
datasetpipeline-0.2.1.dist-info/entry_points.txt
datasetpipeline-0.2.1.dist-info/licenses/LICENSE
datasetpipeline-0.2.1.dist-info/RECORD
