Metadata-Version: 2.4
Name: datasetpipeline
Version: 0.2.1
Summary: A data processing and analysis pipeline designed to handle various jobs related to data transformation, quality assessment, deduplication, and formatting. The pipeline can be configured and executed using YAML configuration files.
Project-URL: Homepage, https://github.com/subhayu99/datasetpipeline
Project-URL: Documentation, https://github.com/subhayu99/datasetpipeline#readme
Project-URL: Repository, https://github.com/subhayu99/datasetpipeline
Project-URL: Bug Tracker, https://github.com/subhayu99/datasetpipeline/issues
Author-email: Subhayu Kumar Bala <balasubhayu99@gmail.com>
Maintainer-email: Subhayu Kumar Bala <balasubhayu99@gmail.com>
License: MIT
License-File: LICENSE
Keywords: data-processing,dataset,deduplication,ml,pipeline,quality-analysis
Classifier: Development Status :: 4 - Beta
Classifier: Intended Audience :: Developers
Classifier: Intended Audience :: Science/Research
Classifier: License :: OSI Approved :: MIT License
Classifier: Operating System :: OS Independent
Classifier: Programming Language :: Python :: 3
Classifier: Programming Language :: Python :: 3.10
Classifier: Programming Language :: Python :: 3.11
Classifier: Programming Language :: Python :: 3.12
Classifier: Topic :: Scientific/Engineering :: Artificial Intelligence
Classifier: Topic :: Software Development :: Libraries :: Python Modules
Classifier: Topic :: Text Processing
Requires-Python: >=3.10
Requires-Dist: datasets==3.6.0
Requires-Dist: faiss-cpu==1.11.0
Requires-Dist: fuzzywuzzy==0.18.0
Requires-Dist: huggingface-hub==0.32.0
Requires-Dist: langchain-community==0.3.24
Requires-Dist: langchain-core==0.3.61
Requires-Dist: loguru==0.7.3
Requires-Dist: numpy==2.2.6
Requires-Dist: onnxruntime==1.22.0
Requires-Dist: openai==1.82.0
Requires-Dist: pandas==2.2.3
Requires-Dist: pydantic==2.11.5
Requires-Dist: python-levenshtein==0.27.1
Requires-Dist: retry==0.9.2
Requires-Dist: rich==14.0.0
Requires-Dist: ruamel-yaml
Requires-Dist: sqlalchemy==2.0.41
Requires-Dist: typer==0.15.4
Provides-Extra: all
Requires-Dist: faiss-gpu==1.7.2; extra == 'all'
Requires-Dist: langchain-community==0.3.24; extra == 'all'
Requires-Dist: sentence-transformers==4.1.0; extra == 'all'
Requires-Dist: torch==2.7.0; extra == 'all'
Requires-Dist: transformers==4.52.3; extra == 'all'
Provides-Extra: dev
Requires-Dist: black==25.1.0; extra == 'dev'
Requires-Dist: build==1.2.2.post1; extra == 'dev'
Requires-Dist: flake8==7.2.0; extra == 'dev'
Requires-Dist: ipykernel==6.29.5; extra == 'dev'
Requires-Dist: mypy==1.15.0; extra == 'dev'
Requires-Dist: pytest-cov==6.1.1; extra == 'dev'
Requires-Dist: pytest==8.3.5; extra == 'dev'
Requires-Dist: tabulate==0.9.0; extra == 'dev'
Requires-Dist: twine==6.1.0; extra == 'dev'
Provides-Extra: full
Requires-Dist: langchain-community==0.3.24; extra == 'full'
Requires-Dist: sentence-transformers==4.1.0; extra == 'full'
Requires-Dist: torch==2.7.0; extra == 'full'
Requires-Dist: transformers==4.52.3; extra == 'full'
Provides-Extra: gpu
Requires-Dist: faiss-gpu==1.7.2; extra == 'gpu'
Requires-Dist: torch[cuda]==2.7.0; extra == 'gpu'
